README.md
setup.cfg
setup.py
integrity_to_sqlite/__init__.py
integrity_to_sqlite/__main__.py
integrity_to_sqlite/main.py
integrity_to_sqlite.egg-info/PKG-INFO
integrity_to_sqlite.egg-info/SOURCES.txt
integrity_to_sqlite.egg-info/dependency_links.txt
integrity_to_sqlite.egg-info/entry_points.txt
integrity_to_sqlite.egg-info/requires.txt
integrity_to_sqlite.egg-info/top_level.txt