Metadata-Version: 1.1
Name: integrity-to-sqlite
Version: 0.9
Summary: store `ls -l`, `md5sum` and `sha256sum` to sqlite
Home-page: https://github.com/jeremiahsavage/integrity_to_sqlite
Author: Jeremiah H. Savage
Author-email: jeremiahsavage@gmail.com
License: Apache 2.0
Platform: UNKNOWN
Classifier: Development Status :: 3 - Alpha
Classifier: Intended Audience :: Developers
Classifier: License :: OSI Approved :: Apache Software License
Classifier: Programming Language :: Python
Classifier: Programming Language :: Python :: 2
Classifier: Programming Language :: Python :: 3
